LICENSE
MANIFEST.in
README.rst
setup.py
summon_process/__init__.py
summon_process/orchestrator.py
summon_process/utils.py
summon_process.egg-info/PKG-INFO
summon_process.egg-info/SOURCES.txt
summon_process.egg-info/dependency_links.txt
summon_process.egg-info/not-zip-safe
summon_process.egg-info/top_level.txt
summon_process/executors/__init__.py
summon_process/executors/http_coordinated_executor.py
summon_process/executors/output_coordinated_executor.py
summon_process/executors/simple_executor.py
summon_process/executors/tcp_coordinated_executor.py