Metadata-Version: 1.0
Name: summon-process
Version: 0.1.2
Summary: Process coordinator for tests
Home-page: https://github.com/mlen/summon_process
Author: Mateusz Lenik
Author-email: mlen@mlen.pl
License: LGPL
Platform: UNKNOWN
